kozmoserver_mlflow/__init__.py
kozmoserver_mlflow/codecs.py
kozmoserver_mlflow/metadata.py
kozmoserver_mlflow/runtime.py
kozmoserver_mlflow/version.py
kozmoserver_mlflow-0.1.0.dev1.dist-info/LICENSE
kozmoserver_mlflow-0.1.0.dev1.dist-info/METADATA
kozmoserver_mlflow-0.1.0.dev1.dist-info/WHEEL
kozmoserver_mlflow-0.1.0.dev1.dist-info/RECORD
